roipy/__init__.py
roipy/animation/__init__.py
roipy/animation/animation.py
roipy/plotting/__init__.py
roipy/plotting/plotting.py
roipy/plotting/utils.py
roipy-1.3.8.dist-info/LICENSE
roipy-1.3.8.dist-info/METADATA
roipy-1.3.8.dist-info/WHEEL
roipy-1.3.8.dist-info/top_level.txt
roipy-1.3.8.dist-info/RECORD
